{
    "gui": {
        "editor_gaphas": {
            "name": {
                "rel_pos": {
                    "__jsonqualname__": "__builtin__.tuple", 
                    "items": [
                        1.0483580212179007, 
                        1.0483580212179007
                    ]
                }, 
                "size": {
                    "__jsonqualname__": "__builtin__.tuple", 
                    "items": [
                        20.967160424357964, 
                        10.483580212178982
                    ]
                }
            }, 
            "rel_pos": {
                "__jsonqualname__": "__builtin__.tuple", 
                "items": [
                    48.42152558917794, 
                    56.07050705099016
                ]
            }, 
            "size": {
                "__jsonqualname__": "__builtin__.tuple", 
                "items": [
                    26.208950530447453, 
                    26.208950530447453
                ]
            }
        }
    }, 
    "income": {
        "gui": {
            "editor_gaphas": {
                "rel_pos": {
                    "__jsonqualname__": "__builtin__.tuple", 
                    "items": [
                        3.479093494518409, 
                        0.524179010608949
                    ]
                }
            }
        }
    }, 
    "input_data_port0": {
        "gui": {
            "editor_gaphas": {
                "rel_pos": {
                    "__jsonqualname__": "__builtin__.tuple", 
                    "items": [
                        0.524179010608949, 
                        4.696293429770549
                    ]
                }
            }
        }
    }, 
    "outcome-1": {
        "gui": {
            "editor_gaphas": {
                "rel_pos": {
                    "__jsonqualname__": "__builtin__.tuple", 
                    "items": [
                        23.58805547740271, 
                        0.524179010608949
                    ]
                }
            }
        }
    }, 
    "outcome-2": {
        "gui": {
            "editor_gaphas": {
                "rel_pos": {
                    "__jsonqualname__": "__builtin__.tuple", 
                    "items": [
                        21.49133943496691, 
                        0.524179010608949
                    ]
                }
            }
        }
    }, 
    "outcome0": {
        "gui": {
            "editor_gaphas": {
                "rel_pos": {
                    "__jsonqualname__": "__builtin__.tuple", 
                    "items": [
                        25.684771519838502, 
                        2.620895053044745
                    ]
                }
            }
        }
    }, 
    "output_data_port1": {
        "gui": {
            "editor_gaphas": {
                "rel_pos": {
                    "__jsonqualname__": "__builtin__.tuple", 
                    "items": [
                        19.375112010609207, 
                        0.524179010608949
                    ]
                }
            }
        }
    }
}